<?xml version="1.0" encoding="UTF-8" ?>
<annotation>
  <folder>RGB200W_202006292031_116444762403679213.jpg</folder>
  <filename>RGB200W_202006292031_116444762403679213.jpg</filename>
  <path>http://172.18.39.209:9000/aliimages1999999990/RGB200W_202006292031_116444762403679213.jpg</path>
  <source>
    <database>Unknown</database>
  </source>
  <size>
    <width>642</width>
    <height>361</height>
    <depth>0</depth>
  </size>
  <segmented>0</segmented>
  <object>
    <name>wire</name>
    <pose>Unspecified</pose>
    <truncated>0</truncated>
    <difficult>0</difficult>
    <bndbox>
      <xmin>321.36</xmin>
      <ymin>183.64</ymin>
      <xmax>428.64</xmax>
      <ymax>206.82</ymax>
    </bndbox>
  </object>
  <object>
    <name>washing_machine</name>
    <pose>Unspecified</pose>
    <truncated>0</truncated>
    <difficult>0</difficult>
    <bndbox>
      <xmin>331.36</xmin>
      <ymin>0.00</ymin>
      <xmax>641.82</xmax>
      <ymax>191.82</ymax>
    </bndbox>
  </object>
  <object>
    <name>dining_table</name>
    <pose>Unspecified</pose>
    <truncated>0</truncated>
    <difficult>0</difficult>
    <bndbox>
      <xmin>45.45</xmin>
      <ymin>76.82</ymin>
      <xmax>177.73</xmax>
      <ymax>185.45</ymax>
    </bndbox>
  </object>
</annotation>