<?xml version="1.0" encoding="UTF-8" ?>
<annotation>
  <folder>2021101601</folder>
  <filename>rBkNzWBnDz6IJtD4AABl8Gq5QHEAAAIjQIvRF4AAGYI726.png</filename>
  <path>http://172.18.39.209:9000/aliimages/2021101601/rBkNzWBnDz6IJtD4AABl8Gq5QHEAAAIjQIvRF4AAGYI726.png</path>
  <source>
    <database>Unknown</database>
  </source>
  <size>
    <width>2440</width>
    <height>1611</height>
    <depth>0</depth>
  </size>
  <segmented>0</segmented>
  <object>
    <name>door_anno</name>
    <pose>Unspecified</pose>
    <truncated>0</truncated>
    <difficult>0</difficult>
    <bndbox>
      <xmin>1008.89</xmin>
      <ymin>596.01</ymin>
      <xmax>1076.27</xmax>
      <ymax>620.19</ymax>
    </bndbox>
  </object>
  <object>
    <name>door_anno</name>
    <pose>Unspecified</pose>
    <truncated>0</truncated>
    <difficult>0</difficult>
    <bndbox>
      <xmin>756.67</xmin>
      <ymin>445.71</ymin>
      <xmax>789.49</xmax>
      <ymax>535.54</ymax>
    </bndbox>
  </object>
  <object>
    <name>door_anno</name>
    <pose>Unspecified</pose>
    <truncated>0</truncated>
    <difficult>0</difficult>
    <bndbox>
      <xmin>1342.31</xmin>
      <ymin>597.73</ymin>
      <xmax>1409.69</xmax>
      <ymax>621.92</ymax>
    </bndbox>
  </object>
  <object>
    <name>door_anno</name>
    <pose>Unspecified</pose>
    <truncated>0</truncated>
    <difficult>0</difficult>
    <bndbox>
      <xmin>1255.93</xmin>
      <ymin>748.03</ymin>
      <xmax>1280.12</xmax>
      <ymax>817.13</ymax>
    </bndbox>
  </object>
  <object>
    <name>door_anno</name>
    <pose>Unspecified</pose>
    <truncated>0</truncated>
    <difficult>0</difficult>
    <bndbox>
      <xmin>1454.60</xmin>
      <ymin>934.61</ymin>
      <xmax>1530.61</xmax>
      <ymax>958.79</ymax>
    </bndbox>
  </object>
  <object>
    <name>door_anno</name>
    <pose>Unspecified</pose>
    <truncated>0</truncated>
    <difficult>0</difficult>
    <bndbox>
      <xmin>1262.84</xmin>
      <ymin>623.65</ymin>
      <xmax>1292.21</xmax>
      <ymax>701.39</ymax>
    </bndbox>
  </object>
  <object>
    <name>room</name>
    <pose>Unspecified</pose>
    <truncated>0</truncated>
    <difficult>0</difficult>
    <bndbox>
      <xmin>1271.48</xmin>
      <ymin>437.07</ymin>
      <xmax>1544.44</xmax>
      <ymax>613.28</ymax>
    </bndbox>
  </object>
  <object>
    <name>room</name>
    <pose>Unspecified</pose>
    <truncated>0</truncated>
    <difficult>0</difficult>
    <bndbox>
      <xmin>1568.62</xmin>
      <ymin>430.16</ymin>
      <xmax>2074.79</xmax>
      <ymax>732.48</ymax>
    </bndbox>
  </object>
  <object>
    <name>room</name>
    <pose>Unspecified</pose>
    <truncated>0</truncated>
    <difficult>0</difficult>
    <bndbox>
      <xmin>1444.24</xmin>
      <ymin>739.39</ymin>
      <xmax>1881.31</xmax>
      <ymax>948.43</ymax>
    </bndbox>
  </object>
  <object>
    <name>room</name>
    <pose>Unspecified</pose>
    <truncated>0</truncated>
    <difficult>0</difficult>
    <bndbox>
      <xmin>1268.03</xmin>
      <ymin>730.76</ymin>
      <xmax>1430.42</xmax>
      <ymax>881.05</ymax>
    </bndbox>
  </object>
  <object>
    <name>room</name>
    <pose>Unspecified</pose>
    <truncated>0</truncated>
    <difficult>0</difficult>
    <bndbox>
      <xmin>697.93</xmin>
      <ymin>609.83</ymin>
      <xmax>1091.82</xmax>
      <ymax>887.96</ymax>
    </bndbox>
  </object>
  <object>
    <name>room</name>
    <pose>Unspecified</pose>
    <truncated>0</truncated>
    <difficult>0</difficult>
    <bndbox>
      <xmin>376.61</xmin>
      <ymin>433.62</ymin>
      <xmax>767.03</xmax>
      <ymax>773.95</ymax>
    </bndbox>
  </object>
  <object>
    <name>room</name>
    <pose>Unspecified</pose>
    <truncated>0</truncated>
    <difficult>0</difficult>
    <bndbox>
      <xmin>1255.93</xmin>
      <ymin>950.16</ymin>
      <xmax>1955.59</xmax>
      <ymax>1309.49</ymax>
    </bndbox>
  </object>
  <object>
    <name>bed</name>
    <pose>Unspecified</pose>
    <truncated>0</truncated>
    <difficult>0</difficult>
    <bndbox>
      <xmin>1751.74</xmin>
      <ymin>431.89</ymin>
      <xmax>1971.14</xmax>
      <ymax>615.01</ymax>
    </bndbox>
  </object>
</annotation>