<?xml version="1.0" encoding="UTF-8" ?>
<annotation>
  <folder>2021101601</folder>
  <filename>rBkNzmCOz_CILU5iAACC8E2BtQoAAAQnQBx5jYAAIMI454.png</filename>
  <path>http://172.18.39.209:9000/aliimages/2021101601/rBkNzmCOz_CILU5iAACC8E2BtQoAAAQnQBx5jYAAIMI454.png</path>
  <source>
    <database>Unknown</database>
  </source>
  <size>
    <width>1750</width>
    <height>2614</height>
    <depth>0</depth>
  </size>
  <segmented>0</segmented>
  <object>
    <name>door_anno</name>
    <pose>Unspecified</pose>
    <truncated>0</truncated>
    <difficult>0</difficult>
    <bndbox>
      <xmin>794.22</xmin>
      <ymin>1471.96</ymin>
      <xmax>819.00</xmax>
      <ymax>1536.39</ymax>
    </bndbox>
  </object>
  <object>
    <name>door_anno</name>
    <pose>Unspecified</pose>
    <truncated>0</truncated>
    <difficult>0</difficult>
    <bndbox>
      <xmin>982.55</xmin>
      <ymin>1348.06</ymin>
      <xmax>1007.33</xmax>
      <ymax>1422.40</ymax>
    </bndbox>
  </object>
  <object>
    <name>door_anno</name>
    <pose>Unspecified</pose>
    <truncated>0</truncated>
    <difficult>0</difficult>
    <bndbox>
      <xmin>696.33</xmin>
      <ymin>1651.62</ymin>
      <xmax>726.07</xmax>
      <ymax>1723.48</ymax>
    </bndbox>
  </object>
  <object>
    <name>door_anno</name>
    <pose>Unspecified</pose>
    <truncated>0</truncated>
    <difficult>0</difficult>
    <bndbox>
      <xmin>903.25</xmin>
      <ymin>1697.47</ymin>
      <xmax>926.79</xmax>
      <ymax>1765.61</ymax>
    </bndbox>
  </object>
  <object>
    <name>door_anno</name>
    <pose>Unspecified</pose>
    <truncated>0</truncated>
    <difficult>0</difficult>
    <bndbox>
      <xmin>932.99</xmin>
      <ymin>2020.85</ymin>
      <xmax>1006.09</xmax>
      <ymax>2043.15</ymax>
    </bndbox>
  </object>
  <object>
    <name>door_anno</name>
    <pose>Unspecified</pose>
    <truncated>0</truncated>
    <difficult>0</difficult>
    <bndbox>
      <xmin>902.01</xmin>
      <ymin>910.68</ymin>
      <xmax>973.87</xmax>
      <ymax>930.51</ymax>
    </bndbox>
  </object>
  <object>
    <name>room</name>
    <pose>Unspecified</pose>
    <truncated>0</truncated>
    <difficult>0</difficult>
    <bndbox>
      <xmin>882.19</xmin>
      <ymin>311.00</ymin>
      <xmax>1343.10</xmax>
      <ymax>916.88</ymax>
    </bndbox>
  </object>
  <object>
    <name>room</name>
    <pose>Unspecified</pose>
    <truncated>0</truncated>
    <difficult>0</difficult>
    <bndbox>
      <xmin>999.89</xmin>
      <ymin>923.07</ymin>
      <xmax>1348.06</xmax>
      <ymax>1324.52</ymax>
    </bndbox>
  </object>
  <object>
    <name>room</name>
    <pose>Unspecified</pose>
    <truncated>0</truncated>
    <difficult>0</difficult>
    <bndbox>
      <xmin>980.07</xmin>
      <ymin>1329.47</ymin>
      <xmax>1354.26</xmax>
      <ymax>1692.51</ymax>
    </bndbox>
  </object>
  <object>
    <name>bed</name>
    <pose>Unspecified</pose>
    <truncated>0</truncated>
    <difficult>0</difficult>
    <bndbox>
      <xmin>1073.00</xmin>
      <ymin>1494.27</ymin>
      <xmax>1248.94</xmax>
      <ymax>1692.51</ymax>
    </bndbox>
  </object>
  <object>
    <name>room</name>
    <pose>Unspecified</pose>
    <truncated>0</truncated>
    <difficult>0</difficult>
    <bndbox>
      <xmin>640.58</xmin>
      <ymin>951.57</ymin>
      <xmax>866.08</xmax>
      <ymax>1224.16</ymax>
    </bndbox>
  </object>
  <object>
    <name>door_anno</name>
    <pose>Unspecified</pose>
    <truncated>0</truncated>
    <difficult>0</difficult>
    <bndbox>
      <xmin>859.88</xmin>
      <ymin>997.42</ymin>
      <xmax>882.19</xmax>
      <ymax>1082.91</ymax>
    </bndbox>
  </object>
  <object>
    <name>room</name>
    <pose>Unspecified</pose>
    <truncated>0</truncated>
    <difficult>0</difficult>
    <bndbox>
      <xmin>641.82</xmin>
      <ymin>1339.39</ymin>
      <xmax>802.89</xmax>
      <ymax>1550.02</ymax>
    </bndbox>
  </object>
  <object>
    <name>room</name>
    <pose>Unspecified</pose>
    <truncated>0</truncated>
    <difficult>0</difficult>
    <bndbox>
      <xmin>444.81</xmin>
      <ymin>1556.22</ymin>
      <xmax>705.01</xmax>
      <ymax>1810.22</ymax>
    </bndbox>
  </object>
  <object>
    <name>room</name>
    <pose>Unspecified</pose>
    <truncated>0</truncated>
    <difficult>0</difficult>
    <bndbox>
      <xmin>899.53</xmin>
      <ymin>1703.66</ymin>
      <xmax>1317.08</xmax>
      <ymax>2032.00</ymax>
    </bndbox>
  </object>
  <object>
    <name>room</name>
    <pose>Unspecified</pose>
    <truncated>0</truncated>
    <difficult>0</difficult>
    <bndbox>
      <xmin>887.14</xmin>
      <ymin>2041.91</ymin>
      <xmax>1310.89</xmax>
      <ymax>2316.98</ymax>
    </bndbox>
  </object>
  <object>
    <name>door_anno</name>
    <pose>Unspecified</pose>
    <truncated>0</truncated>
    <difficult>0</difficult>
    <bndbox>
      <xmin>973.87</xmin>
      <ymin>1045.74</ymin>
      <xmax>1011.05</xmax>
      <ymax>1224.16</ymax>
    </bndbox>
  </object>
</annotation>