<?xml version="1.0" encoding="UTF-8" ?>
<annotation>
  <folder>2021101601</folder>
  <filename>rBkNzGAMFAOIVPaSAABjFVl2-2oAAAFKwCuQm0AAGMt594.png</filename>
  <path>http://172.18.39.209:9000/aliimages/2021101601/rBkNzGAMFAOIVPaSAABjFVl2-2oAAAFKwCuQm0AAGMt594.png</path>
  <source>
    <database>Unknown</database>
  </source>
  <size>
    <width>1994</width>
    <height>1622</height>
    <depth>0</depth>
  </size>
  <segmented>0</segmented>
  <object>
    <name>door_anno</name>
    <pose>Unspecified</pose>
    <truncated>0</truncated>
    <difficult>0</difficult>
    <bndbox>
      <xmin>1079.14</xmin>
      <ymin>543.81</ymin>
      <xmax>1135.64</xmax>
      <ymax>563.58</ymax>
    </bndbox>
  </object>
  <object>
    <name>door_anno</name>
    <pose>Unspecified</pose>
    <truncated>0</truncated>
    <difficult>0</difficult>
    <bndbox>
      <xmin>973.21</xmin>
      <ymin>569.23</ymin>
      <xmax>997.22</xmax>
      <ymax>641.27</ymax>
    </bndbox>
  </object>
  <object>
    <name>door_anno</name>
    <pose>Unspecified</pose>
    <truncated>0</truncated>
    <difficult>0</difficult>
    <bndbox>
      <xmin>723.19</xmin>
      <ymin>559.35</ymin>
      <xmax>779.69</xmax>
      <ymax>576.30</ymax>
    </bndbox>
  </object>
  <object>
    <name>door_anno</name>
    <pose>Unspecified</pose>
    <truncated>0</truncated>
    <difficult>0</difficult>
    <bndbox>
      <xmin>639.86</xmin>
      <ymin>584.77</ymin>
      <xmax>659.63</xmax>
      <ymax>656.81</ymax>
    </bndbox>
  </object>
  <object>
    <name>room</name>
    <pose>Unspecified</pose>
    <truncated>0</truncated>
    <difficult>0</difficult>
    <bndbox>
      <xmin>987.33</xmin>
      <ymin>367.25</ymin>
      <xmax>1142.70</xmax>
      <ymax>543.81</ymax>
    </bndbox>
  </object>
  <object>
    <name>room</name>
    <pose>Unspecified</pose>
    <truncated>0</truncated>
    <difficult>0</difficult>
    <bndbox>
      <xmin>1149.77</xmin>
      <ymin>298.04</ymin>
      <xmax>1498.65</xmax>
      <ymax>649.75</ymax>
    </bndbox>
  </object>
  <object>
    <name>room</name>
    <pose>Unspecified</pose>
    <truncated>0</truncated>
    <difficult>0</difficult>
    <bndbox>
      <xmin>569.23</xmin>
      <ymin>303.69</ymin>
      <xmax>806.53</xmax>
      <ymax>563.58</ymax>
    </bndbox>
  </object>
  <object>
    <name>room</name>
    <pose>Unspecified</pose>
    <truncated>0</truncated>
    <difficult>0</difficult>
    <bndbox>
      <xmin>293.80</xmin>
      <ymin>307.92</ymin>
      <xmax>566.41</xmax>
      <ymax>676.58</ymax>
    </bndbox>
  </object>
  <object>
    <name>room</name>
    <pose>Unspecified</pose>
    <truncated>0</truncated>
    <difficult>0</difficult>
    <bndbox>
      <xmin>813.59</xmin>
      <ymin>399.73</ymin>
      <xmax>985.92</xmax>
      <ymax>563.58</ymax>
    </bndbox>
  </object>
  <object>
    <name>room</name>
    <pose>Unspecified</pose>
    <truncated>0</truncated>
    <difficult>0</difficult>
    <bndbox>
      <xmin>1004.28</xmin>
      <ymin>656.81</ymin>
      <xmax>1494.41</xmax>
      <ymax>1081.97</ymax>
    </bndbox>
  </object>
  <object>
    <name>room</name>
    <pose>Unspecified</pose>
    <truncated>0</truncated>
    <difficult>0</difficult>
    <bndbox>
      <xmin>764.16</xmin>
      <ymin>799.47</ymin>
      <xmax>998.63</xmax>
      <ymax>1221.80</ymax>
    </bndbox>
  </object>
  <object>
    <name>bed</name>
    <pose>Unspecified</pose>
    <truncated>0</truncated>
    <difficult>0</difficult>
    <bndbox>
      <xmin>1279.72</xmin>
      <ymin>374.31</ymin>
      <xmax>1487.35</xmax>
      <ymax>548.05</ymax>
    </bndbox>
  </object>
  <object>
    <name>door_anno</name>
    <pose>Unspecified</pose>
    <truncated>0</truncated>
    <difficult>0</difficult>
    <bndbox>
      <xmin>974.62</xmin>
      <ymin>682.23</ymin>
      <xmax>1004.28</xmax>
      <ymax>788.17</ymax>
    </bndbox>
  </object>
</annotation>