<?xml version="1.0" encoding="UTF-8" ?>
<annotation>
  <folder>2021101601</folder>
  <filename>rBkNzWBCiP-IQW09AABcruP7yV4AAAAVAHvcRMAAFzG064.png</filename>
  <path>http://172.18.39.209:9000/aliimages/2021101601/rBkNzWBCiP-IQW09AABcruP7yV4AAAAVAHvcRMAAFzG064.png</path>
  <source>
    <database>Unknown</database>
  </source>
  <size>
    <width>2100</width>
    <height>1563</height>
    <depth>0</depth>
  </size>
  <segmented>0</segmented>
  <object>
    <name>door_anno</name>
    <pose>Unspecified</pose>
    <truncated>0</truncated>
    <difficult>0</difficult>
    <bndbox>
      <xmin>1232.58</xmin>
      <ymin>514.44</ymin>
      <xmax>1306.92</xmax>
      <ymax>533.77</ymax>
    </bndbox>
  </object>
  <object>
    <name>door_anno</name>
    <pose>Unspecified</pose>
    <truncated>0</truncated>
    <difficult>0</difficult>
    <bndbox>
      <xmin>741.93</xmin>
      <ymin>731.52</ymin>
      <xmax>805.86</xmax>
      <ymax>752.34</ymax>
    </bndbox>
  </object>
  <object>
    <name>door_anno</name>
    <pose>Unspecified</pose>
    <truncated>0</truncated>
    <difficult>0</difficult>
    <bndbox>
      <xmin>651.23</xmin>
      <ymin>764.23</ymin>
      <xmax>675.02</xmax>
      <ymax>832.63</ymax>
    </bndbox>
  </object>
  <object>
    <name>door_anno</name>
    <pose>Unspecified</pose>
    <truncated>0</truncated>
    <difficult>0</difficult>
    <bndbox>
      <xmin>688.40</xmin>
      <ymin>848.98</ymin>
      <xmax>761.26</xmax>
      <ymax>874.26</ymax>
    </bndbox>
  </object>
  <object>
    <name>door_anno</name>
    <pose>Unspecified</pose>
    <truncated>0</truncated>
    <difficult>0</difficult>
    <bndbox>
      <xmin>786.53</xmin>
      <ymin>846.01</ymin>
      <xmax>853.44</xmax>
      <ymax>875.74</ymax>
    </bndbox>
  </object>
  <object>
    <name>room</name>
    <pose>Unspecified</pose>
    <truncated>0</truncated>
    <difficult>0</difficult>
    <bndbox>
      <xmin>1162.70</xmin>
      <ymin>298.85</ymin>
      <xmax>1451.15</xmax>
      <ymax>514.44</ymax>
    </bndbox>
  </object>
  <object>
    <name>room</name>
    <pose>Unspecified</pose>
    <truncated>0</truncated>
    <difficult>0</difficult>
    <bndbox>
      <xmin>1005.10</xmin>
      <ymin>535.26</ymin>
      <xmax>1347.07</xmax>
      <ymax>1101.74</ymax>
    </bndbox>
  </object>
  <object>
    <name>room</name>
    <pose>Unspecified</pose>
    <truncated>0</truncated>
    <difficult>0</difficult>
    <bndbox>
      <xmin>779.10</xmin>
      <ymin>862.36</ymin>
      <xmax>1037.81</xmax>
      <ymax>1220.69</ymax>
    </bndbox>
  </object>
  <object>
    <name>room</name>
    <pose>Unspecified</pose>
    <truncated>0</truncated>
    <difficult>0</difficult>
    <bndbox>
      <xmin>526.34</xmin>
      <ymin>871.28</ymin>
      <xmax>759.77</xmax>
      <ymax>1234.07</ymax>
    </bndbox>
  </object>
  <object>
    <name>room</name>
    <pose>Unspecified</pose>
    <truncated>0</truncated>
    <difficult>0</difficult>
    <bndbox>
      <xmin>677.99</xmin>
      <ymin>624.47</ymin>
      <xmax>838.57</xmax>
      <ymax>740.44</ymax>
    </bndbox>
  </object>
  <object>
    <name>room</name>
    <pose>Unspecified</pose>
    <truncated>0</truncated>
    <difficult>0</difficult>
    <bndbox>
      <xmin>294.39</xmin>
      <ymin>556.07</ymin>
      <xmax>660.15</xmax>
      <ymax>862.36</ymax>
    </bndbox>
  </object>
  <object>
    <name>door_anno</name>
    <pose>Unspecified</pose>
    <truncated>0</truncated>
    <difficult>0</difficult>
    <bndbox>
      <xmin>963.47</xmin>
      <ymin>734.49</ymin>
      <xmax>999.15</xmax>
      <ymax>841.55</ymax>
    </bndbox>
  </object>
  <object>
    <name>bed</name>
    <pose>Unspecified</pose>
    <truncated>0</truncated>
    <difficult>0</difficult>
    <bndbox>
      <xmin>300.34</xmin>
      <ymin>624.47</ymin>
      <xmax>514.44</xmax>
      <ymax>799.92</ymax>
    </bndbox>
  </object>
</annotation>