<?xml version="1.0" encoding="UTF-8" ?>
<annotation>
  <folder>RGB200W_202006292027_116444804348898172.jpg</folder>
  <filename>RGB200W_202006292027_116444804348898172.jpg</filename>
  <path>http://172.18.39.209:9000/aliimages1999999996/RGB200W_202006292027_116444804348898172.jpg</path>
  <source>
    <database>Unknown</database>
  </source>
  <size>
    <width>642</width>
    <height>361</height>
    <depth>0</depth>
  </size>
  <segmented>0</segmented>
  <object>
    <name>wire</name>
    <pose>Unspecified</pose>
    <truncated>0</truncated>
    <difficult>0</difficult>
    <bndbox>
      <xmin>394.55</xmin>
      <ymin>141.36</ymin>
      <xmax>460.91</xmax>
      <ymax>207.73</ymax>
    </bndbox>
  </object>
  <object>
    <name>chair_base</name>
    <pose>Unspecified</pose>
    <truncated>0</truncated>
    <difficult>0</difficult>
    <bndbox>
      <xmin>479.55</xmin>
      <ymin>188.18</ymin>
      <xmax>641.82</xmax>
      <ymax>211.82</ymax>
    </bndbox>
  </object>
  <object>
    <name>refrigerator_1</name>
    <pose>Unspecified</pose>
    <truncated>0</truncated>
    <difficult>0</difficult>
    <bndbox>
      <xmin>110.45</xmin>
      <ymin>0.00</ymin>
      <xmax>260.00</xmax>
      <ymax>205.00</ymax>
    </bndbox>
  </object>
  <object>
    <name>charger</name>
    <pose>Unspecified</pose>
    <truncated>0</truncated>
    <difficult>0</difficult>
    <bndbox>
      <xmin>349.55</xmin>
      <ymin>186.82</ymin>
      <xmax>381.82</xmax>
      <ymax>207.27</ymax>
    </bndbox>
  </object>
  <object>
    <name>wire</name>
    <pose>Unspecified</pose>
    <truncated>0</truncated>
    <difficult>0</difficult>
    <bndbox>
      <xmin>510.91</xmin>
      <ymin>92.27</ymin>
      <xmax>570.91</xmax>
      <ymax>177.73</ymax>
    </bndbox>
  </object>
  <object>
    <name>wire</name>
    <pose>Unspecified</pose>
    <truncated>0</truncated>
    <difficult>0</difficult>
    <bndbox>
      <xmin>459.09</xmin>
      <ymin>59.09</ymin>
      <xmax>495.91</xmax>
      <ymax>142.73</ymax>
    </bndbox>
  </object>
  <object>
    <name>TV_stand</name>
    <pose>Unspecified</pose>
    <truncated>0</truncated>
    <difficult>0</difficult>
    <bndbox>
      <xmin>406.82</xmin>
      <ymin>33.64</ymin>
      <xmax>641.82</xmax>
      <ymax>204.55</ymax>
    </bndbox>
  </object>
  <object>
    <name>wire</name>
    <pose>Unspecified</pose>
    <truncated>0</truncated>
    <difficult>0</difficult>
    <bndbox>
      <xmin>404.09</xmin>
      <ymin>53.18</ymin>
      <xmax>439.55</xmax>
      <ymax>103.64</ymax>
    </bndbox>
  </object>
</annotation>