<?xml version="1.0" encoding="UTF-8" ?>
<annotation>
  <folder>2021101601</folder>
  <filename>rBkNzWBltE6IQ3DhAABJKN_ra2wAAAKMAN5Pf0AAElA120.png</filename>
  <path>http://172.18.39.209:9000/aliimages/2021101601/rBkNzWBltE6IQ3DhAABJKN_ra2wAAAKMAN5Pf0AAElA120.png</path>
  <source>
    <database>Unknown</database>
  </source>
  <size>
    <width>2085</width>
    <height>1354</height>
    <depth>0</depth>
  </size>
  <segmented>0</segmented>
  <object>
    <name>door_anno</name>
    <pose>Unspecified</pose>
    <truncated>0</truncated>
    <difficult>0</difficult>
    <bndbox>
      <xmin>1144.06</xmin>
      <ymin>612.63</ymin>
      <xmax>1164.73</xmax>
      <ymax>683.49</ymax>
    </bndbox>
  </object>
  <object>
    <name>door_anno</name>
    <pose>Unspecified</pose>
    <truncated>0</truncated>
    <difficult>0</difficult>
    <bndbox>
      <xmin>1042.20</xmin>
      <ymin>594.91</ymin>
      <xmax>1126.35</xmax>
      <ymax>611.15</ymax>
    </bndbox>
  </object>
  <object>
    <name>door_anno</name>
    <pose>Unspecified</pose>
    <truncated>0</truncated>
    <difficult>0</difficult>
    <bndbox>
      <xmin>1241.49</xmin>
      <ymin>501.91</ymin>
      <xmax>1257.73</xmax>
      <ymax>581.63</ymax>
    </bndbox>
  </object>
  <object>
    <name>door_anno</name>
    <pose>Unspecified</pose>
    <truncated>0</truncated>
    <difficult>0</difficult>
    <bndbox>
      <xmin>962.49</xmin>
      <ymin>491.58</ymin>
      <xmax>1027.44</xmax>
      <ymax>509.29</ymax>
    </bndbox>
  </object>
  <object>
    <name>door_anno</name>
    <pose>Unspecified</pose>
    <truncated>0</truncated>
    <difficult>0</difficult>
    <bndbox>
      <xmin>586.06</xmin>
      <ymin>515.20</ymin>
      <xmax>603.77</xmax>
      <ymax>586.06</ymax>
    </bndbox>
  </object>
  <object>
    <name>room</name>
    <pose>Unspecified</pose>
    <truncated>0</truncated>
    <difficult>0</difficult>
    <bndbox>
      <xmin>301.15</xmin>
      <ymin>333.62</ymin>
      <xmax>589.01</xmax>
      <ymax>652.49</ymax>
    </bndbox>
  </object>
  <object>
    <name>bed</name>
    <pose>Unspecified</pose>
    <truncated>0</truncated>
    <difficult>0</difficult>
    <bndbox>
      <xmin>296.72</xmin>
      <ymin>408.91</ymin>
      <xmax>507.82</xmax>
      <ymax>581.63</ymax>
    </bndbox>
  </object>
  <object>
    <name>room</name>
    <pose>Unspecified</pose>
    <truncated>0</truncated>
    <difficult>0</difficult>
    <bndbox>
      <xmin>872.44</xmin>
      <ymin>302.62</ymin>
      <xmax>1155.87</xmax>
      <ymax>497.48</ymax>
    </bndbox>
  </object>
  <object>
    <name>room</name>
    <pose>Unspecified</pose>
    <truncated>0</truncated>
    <difficult>0</difficult>
    <bndbox>
      <xmin>1257.73</xmin>
      <ymin>320.34</ymin>
      <xmax>1669.59</xmax>
      <ymax>593.44</ymax>
    </bndbox>
  </object>
  <object>
    <name>room</name>
    <pose>Unspecified</pose>
    <truncated>0</truncated>
    <difficult>0</difficult>
    <bndbox>
      <xmin>766.15</xmin>
      <ymin>602.29</ymin>
      <xmax>1152.92</xmax>
      <ymax>1000.87</ymax>
    </bndbox>
  </object>
  <object>
    <name>room</name>
    <pose>Unspecified</pose>
    <truncated>0</truncated>
    <difficult>0</difficult>
    <bndbox>
      <xmin>1152.92</xmin>
      <ymin>600.82</ymin>
      <xmax>1657.78</xmax>
      <ymax>1055.49</ymax>
    </bndbox>
  </object>
</annotation>