<?xml version="1.0" encoding="UTF-8" ?>
<annotation>
  <folder>2021101602</folder>
  <filename>rBkNzGBS_h6IJzx2AABkaOcLeWAAAADoAJ3edwAAGSA559.png</filename>
  <path>http://172.18.39.209:9000/aliimages/2021101602/rBkNzGBS_h6IJzx2AABkaOcLeWAAAADoAJ3edwAAGSA559.png</path>
  <source>
    <database>Unknown</database>
  </source>
  <size>
    <width>2215</width>
    <height>1452</height>
    <depth>0</depth>
  </size>
  <segmented>0</segmented>
  <object>
    <name>door_anno</name>
    <pose>Unspecified</pose>
    <truncated>0</truncated>
    <difficult>0</difficult>
    <bndbox>
      <xmin>873.52</xmin>
      <ymin>388.93</ymin>
      <xmax>898.61</xmax>
      <ymax>461.07</ymax>
    </bndbox>
  </object>
  <object>
    <name>door_anno</name>
    <pose>Unspecified</pose>
    <truncated>0</truncated>
    <difficult>0</difficult>
    <bndbox>
      <xmin>716.69</xmin>
      <ymin>559.87</ymin>
      <xmax>733.94</xmax>
      <ymax>632.01</ymax>
    </bndbox>
  </object>
  <object>
    <name>door_anno</name>
    <pose>Unspecified</pose>
    <truncated>0</truncated>
    <difficult>0</difficult>
    <bndbox>
      <xmin>713.55</xmin>
      <ymin>669.64</ymin>
      <xmax>730.81</xmax>
      <ymax>737.08</ymax>
    </bndbox>
  </object>
  <object>
    <name>door_anno</name>
    <pose>Unspecified</pose>
    <truncated>0</truncated>
    <difficult>0</difficult>
    <bndbox>
      <xmin>928.41</xmin>
      <ymin>740.22</ymin>
      <xmax>997.41</xmax>
      <ymax>759.03</ymax>
    </bndbox>
  </object>
  <object>
    <name>door_anno</name>
    <pose>Unspecified</pose>
    <truncated>0</truncated>
    <difficult>0</difficult>
    <bndbox>
      <xmin>1077.39</xmin>
      <ymin>737.08</ymin>
      <xmax>1147.96</xmax>
      <ymax>749.62</ymax>
    </bndbox>
  </object>
  <object>
    <name>door_anno</name>
    <pose>Unspecified</pose>
    <truncated>0</truncated>
    <difficult>0</difficult>
    <bndbox>
      <xmin>1191.87</xmin>
      <ymin>729.24</ymin>
      <xmax>1264.01</xmax>
      <ymax>748.06</ymax>
    </bndbox>
  </object>
  <object>
    <name>door_anno</name>
    <pose>Unspecified</pose>
    <truncated>0</truncated>
    <difficult>0</difficult>
    <bndbox>
      <xmin>1356.54</xmin>
      <ymin>649.26</ymin>
      <xmax>1373.79</xmax>
      <ymax>719.83</ymax>
    </bndbox>
  </object>
  <object>
    <name>room</name>
    <pose>Unspecified</pose>
    <truncated>0</truncated>
    <difficult>0</difficult>
    <bndbox>
      <xmin>1367.52</xmin>
      <ymin>633.57</ymin>
      <xmax>1703.12</xmax>
      <ymax>1069.55</ymax>
    </bndbox>
  </object>
  <object>
    <name>room</name>
    <pose>Unspecified</pose>
    <truncated>0</truncated>
    <difficult>0</difficult>
    <bndbox>
      <xmin>886.06</xmin>
      <ymin>340.31</ymin>
      <xmax>1547.87</xmax>
      <ymax>630.44</ymax>
    </bndbox>
  </object>
  <object>
    <name>room</name>
    <pose>Unspecified</pose>
    <truncated>0</truncated>
    <difficult>0</difficult>
    <bndbox>
      <xmin>487.73</xmin>
      <ymin>448.52</ymin>
      <xmax>708.85</xmax>
      <ymax>647.69</ymax>
    </bndbox>
  </object>
  <object>
    <name>room</name>
    <pose>Unspecified</pose>
    <truncated>0</truncated>
    <difficult>0</difficult>
    <bndbox>
      <xmin>550.46</xmin>
      <ymin>652.39</ymin>
      <xmax>715.12</xmax>
      <ymax>1025.64</ymax>
    </bndbox>
  </object>
  <object>
    <name>room</name>
    <pose>Unspecified</pose>
    <truncated>0</truncated>
    <difficult>0</difficult>
    <bndbox>
      <xmin>724.53</xmin>
      <ymin>752.76</ymin>
      <xmax>1014.66</xmax>
      <ymax>1072.68</ymax>
    </bndbox>
  </object>
  <object>
    <name>room</name>
    <pose>Unspecified</pose>
    <truncated>0</truncated>
    <difficult>0</difficult>
    <bndbox>
      <xmin>1031.91</xmin>
      <ymin>752.76</ymin>
      <xmax>1165.21</xmax>
      <ymax>865.68</ymax>
    </bndbox>
  </object>
  <object>
    <name>room</name>
    <pose>Unspecified</pose>
    <truncated>0</truncated>
    <difficult>0</difficult>
    <bndbox>
      <xmin>1080.53</xmin>
      <ymin>865.68</ymin>
      <xmax>1284.40</xmax>
      <ymax>1077.39</ymax>
    </bndbox>
  </object>
  <object>
    <name>bed</name>
    <pose>Unspecified</pose>
    <truncated>0</truncated>
    <difficult>0</difficult>
    <bndbox>
      <xmin>1497.68</xmin>
      <ymin>632.01</ymin>
      <xmax>1659.21</xmax>
      <ymax>834.31</ymax>
    </bndbox>
  </object>
  <object>
    <name>room</name>
    <pose>Unspecified</pose>
    <truncated>0</truncated>
    <difficult>0</difficult>
    <bndbox>
      <xmin>708.85</xmin>
      <ymin>301.10</ymin>
      <xmax>879.79</xmax>
      <ymax>751.19</ymax>
    </bndbox>
  </object>
</annotation>