<?xml version="1.0" encoding="UTF-8" ?>
<annotation>
  <folder>2021101601</folder>
  <filename>rBkNzmBR04WIbTHdAABOvScxWgAAAAMPQPIoWQAAE7V100.png</filename>
  <path>http://172.18.39.209:9000/aliimages/2021101601/rBkNzmBR04WIbTHdAABOvScxWgAAAAMPQPIoWQAAE7V100.png</path>
  <source>
    <database>Unknown</database>
  </source>
  <size>
    <width>1590</width>
    <height>1793</height>
    <depth>0</depth>
  </size>
  <segmented>0</segmented>
  <object>
    <name>door_anno</name>
    <pose>Unspecified</pose>
    <truncated>0</truncated>
    <difficult>0</difficult>
    <bndbox>
      <xmin>1016.55</xmin>
      <ymin>742.99</ymin>
      <xmax>1081.84</xmax>
      <ymax>756.50</ymax>
    </bndbox>
  </object>
  <object>
    <name>door_anno</name>
    <pose>Unspecified</pose>
    <truncated>0</truncated>
    <difficult>0</difficult>
    <bndbox>
      <xmin>844.31</xmin>
      <ymin>747.49</ymin>
      <xmax>915.23</xmax>
      <ymax>763.25</ymax>
    </bndbox>
  </object>
  <object>
    <name>door_anno</name>
    <pose>Unspecified</pose>
    <truncated>0</truncated>
    <difficult>0</difficult>
    <bndbox>
      <xmin>824.04</xmin>
      <ymin>906.22</ymin>
      <xmax>840.93</xmax>
      <ymax>976.02</ymax>
    </bndbox>
  </object>
  <object>
    <name>door_anno</name>
    <pose>Unspecified</pose>
    <truncated>0</truncated>
    <difficult>0</difficult>
    <bndbox>
      <xmin>918.61</xmin>
      <ymin>997.41</ymin>
      <xmax>935.49</xmax>
      <ymax>1067.20</ymax>
    </bndbox>
  </object>
  <object>
    <name>door_anno</name>
    <pose>Unspecified</pose>
    <truncated>0</truncated>
    <difficult>0</difficult>
    <bndbox>
      <xmin>817.29</xmin>
      <ymin>1016.55</ymin>
      <xmax>831.92</xmax>
      <ymax>1081.84</ymax>
    </bndbox>
  </object>
  <object>
    <name>door_anno</name>
    <pose>Unspecified</pose>
    <truncated>0</truncated>
    <difficult>0</difficult>
    <bndbox>
      <xmin>912.98</xmin>
      <ymin>1338.51</ymin>
      <xmax>925.36</xmax>
      <ymax>1412.81</ymax>
    </bndbox>
  </object>
  <object>
    <name>door_anno</name>
    <pose>Unspecified</pose>
    <truncated>0</truncated>
    <difficult>0</difficult>
    <bndbox>
      <xmin>842.06</xmin>
      <ymin>1173.02</ymin>
      <xmax>923.11</xmax>
      <ymax>1193.29</ymax>
    </bndbox>
  </object>
  <object>
    <name>room</name>
    <pose>Unspecified</pose>
    <truncated>0</truncated>
    <difficult>0</difficult>
    <bndbox>
      <xmin>916.36</xmin>
      <ymin>1327.25</ymin>
      <xmax>1095.35</xmax>
      <ymax>1499.49</ymax>
    </bndbox>
  </object>
  <object>
    <name>room</name>
    <pose>Unspecified</pose>
    <truncated>0</truncated>
    <difficult>0</difficult>
    <bndbox>
      <xmin>328.72</xmin>
      <ymin>1230.44</ymin>
      <xmax>911.85</xmax>
      <ymax>1487.11</ymax>
    </bndbox>
  </object>
  <object>
    <name>room</name>
    <pose>Unspecified</pose>
    <truncated>0</truncated>
    <difficult>0</difficult>
    <bndbox>
      <xmin>345.60</xmin>
      <ymin>992.91</ymin>
      <xmax>827.42</xmax>
      <ymax>1232.69</ymax>
    </bndbox>
  </object>
  <object>
    <name>room</name>
    <pose>Unspecified</pose>
    <truncated>0</truncated>
    <difficult>0</difficult>
    <bndbox>
      <xmin>929.86</xmin>
      <ymin>902.85</ymin>
      <xmax>1105.48</xmax>
      <ymax>1090.85</ymax>
    </bndbox>
  </object>
  <object>
    <name>room</name>
    <pose>Unspecified</pose>
    <truncated>0</truncated>
    <difficult>0</difficult>
    <bndbox>
      <xmin>342.23</xmin>
      <ymin>746.37</ymin>
      <xmax>824.04</xmax>
      <ymax>994.03</ymax>
    </bndbox>
  </object>
  <object>
    <name>room</name>
    <pose>Unspecified</pose>
    <truncated>0</truncated>
    <difficult>0</difficult>
    <bndbox>
      <xmin>940.00</xmin>
      <ymin>345.60</ymin>
      <xmax>1223.68</xmax>
      <ymax>750.87</ymax>
    </bndbox>
  </object>
  <object>
    <name>room</name>
    <pose>Unspecified</pose>
    <truncated>0</truncated>
    <difficult>0</difficult>
    <bndbox>
      <xmin>347.85</xmin>
      <ymin>315.21</ymin>
      <xmax>925.36</xmax>
      <ymax>736.24</ymax>
    </bndbox>
  </object>
  <object>
    <name>bed</name>
    <pose>Unspecified</pose>
    <truncated>0</truncated>
    <difficult>0</difficult>
    <bndbox>
      <xmin>473.94</xmin>
      <ymin>1290.10</ymin>
      <xmax>615.78</xmax>
      <ymax>1487.11</ymax>
    </bndbox>
  </object>
</annotation>