<?xml version="1.0" encoding="UTF-8" ?>
<annotation>
  <folder>2021101601</folder>
  <filename>rBkNyWB6n72IbvtuAABJ59w_thIAAAGqQL9VXsAAEn_656.png</filename>
  <path>http://172.18.39.209:9000/aliimages/2021101601/rBkNyWB6n72IbvtuAABJ59w_thIAAAGqQL9VXsAAEn_656.png</path>
  <source>
    <database>Unknown</database>
  </source>
  <size>
    <width>1699</width>
    <height>1538</height>
    <depth>0</depth>
  </size>
  <segmented>0</segmented>
  <object>
    <name>door_anno</name>
    <pose>Unspecified</pose>
    <truncated>0</truncated>
    <difficult>0</difficult>
    <bndbox>
      <xmin>1019.47</xmin>
      <ymin>1025.49</ymin>
      <xmax>1039.93</xmax>
      <ymax>1097.71</ymax>
    </bndbox>
  </object>
  <object>
    <name>door_anno</name>
    <pose>Unspecified</pose>
    <truncated>0</truncated>
    <difficult>0</difficult>
    <bndbox>
      <xmin>925.59</xmin>
      <ymin>964.10</ymin>
      <xmax>996.60</xmax>
      <ymax>983.36</ymax>
    </bndbox>
  </object>
  <object>
    <name>door_anno</name>
    <pose>Unspecified</pose>
    <truncated>0</truncated>
    <difficult>0</difficult>
    <bndbox>
      <xmin>765.51</xmin>
      <ymin>1068.82</ymin>
      <xmax>824.48</xmax>
      <ymax>1084.47</ymax>
    </bndbox>
  </object>
  <object>
    <name>door_anno</name>
    <pose>Unspecified</pose>
    <truncated>0</truncated>
    <difficult>0</difficult>
    <bndbox>
      <xmin>729.40</xmin>
      <ymin>693.29</ymin>
      <xmax>799.21</xmax>
      <ymax>712.55</ymax>
    </bndbox>
  </object>
  <object>
    <name>door_anno</name>
    <pose>Unspecified</pose>
    <truncated>0</truncated>
    <difficult>0</difficult>
    <bndbox>
      <xmin>711.34</xmin>
      <ymin>712.55</ymin>
      <xmax>726.99</xmax>
      <ymax>776.34</ymax>
    </bndbox>
  </object>
  <object>
    <name>door_anno</name>
    <pose>Unspecified</pose>
    <truncated>0</truncated>
    <difficult>0</difficult>
    <bndbox>
      <xmin>701.71</xmin>
      <ymin>976.14</ymin>
      <xmax>718.56</xmax>
      <ymax>1048.36</ymax>
    </bndbox>
  </object>
  <object>
    <name>door_anno</name>
    <pose>Unspecified</pose>
    <truncated>0</truncated>
    <difficult>0</difficult>
    <bndbox>
      <xmin>506.73</xmin>
      <ymin>1072.43</ymin>
      <xmax>527.19</xmax>
      <ymax>1145.85</ymax>
    </bndbox>
  </object>
  <object>
    <name>room</name>
    <pose>Unspecified</pose>
    <truncated>0</truncated>
    <difficult>0</difficult>
    <bndbox>
      <xmin>293.68</xmin>
      <ymin>1054.38</ymin>
      <xmax>516.36</xmax>
      <ymax>1216.86</ymax>
    </bndbox>
  </object>
  <object>
    <name>room</name>
    <pose>Unspecified</pose>
    <truncated>0</truncated>
    <difficult>0</difficult>
    <bndbox>
      <xmin>303.31</xmin>
      <ymin>798.00</ymin>
      <xmax>698.10</xmax>
      <ymax>1051.97</ymax>
    </bndbox>
  </object>
  <object>
    <name>room</name>
    <pose>Unspecified</pose>
    <truncated>0</truncated>
    <difficult>0</difficult>
    <bndbox>
      <xmin>741.43</xmin>
      <ymin>1079.65</ymin>
      <xmax>893.09</xmax>
      <ymax>1224.09</ymax>
    </bndbox>
  </object>
  <object>
    <name>room</name>
    <pose>Unspecified</pose>
    <truncated>0</truncated>
    <difficult>0</difficult>
    <bndbox>
      <xmin>867.81</xmin>
      <ymin>448.95</ymin>
      <xmax>1065.21</xmax>
      <ymax>976.14</ymax>
    </bndbox>
  </object>
  <object>
    <name>room</name>
    <pose>Unspecified</pose>
    <truncated>0</truncated>
    <difficult>0</difficult>
    <bndbox>
      <xmin>1066.41</xmin>
      <ymin>474.23</ymin>
      <xmax>1398.61</xmax>
      <ymax>1122.98</ymax>
    </bndbox>
  </object>
  <object>
    <name>room</name>
    <pose>Unspecified</pose>
    <truncated>0</truncated>
    <difficult>0</difficult>
    <bndbox>
      <xmin>548.85</xmin>
      <ymin>293.68</ymin>
      <xmax>837.72</xmax>
      <ymax>545.24</ymax>
    </bndbox>
  </object>
  <object>
    <name>room</name>
    <pose>Unspecified</pose>
    <truncated>0</truncated>
    <difficult>0</difficult>
    <bndbox>
      <xmin>328.59</xmin>
      <ymin>541.63</ymin>
      <xmax>711.34</xmax>
      <ymax>788.37</ymax>
    </bndbox>
  </object>
  <object>
    <name>bed</name>
    <pose>Unspecified</pose>
    <truncated>0</truncated>
    <difficult>0</difficult>
    <bndbox>
      <xmin>386.36</xmin>
      <ymin>799.21</ymin>
      <xmax>538.02</xmax>
      <ymax>1005.03</ymax>
    </bndbox>
  </object>
</annotation>