<?xml version="1.0" encoding="UTF-8" ?>
<annotation>
  <folder>2021122503</folder>
  <filename>RGB200W_29984CRL30V00066363_1637384675_3146.jpg</filename>
  <path>http://172.18.39.209:9000/aliimages/2021122503/RGB200W_29984CRL30V00066363_1637384675_3146.jpg</path>
  <source>
    <database>Unknown</database>
  </source>
  <size>
    <width>642</width>
    <height>362</height>
    <depth>0</depth>
  </size>
  <segmented>0</segmented>
  <object>
    <name>person_leg</name>
    <pose>Unspecified</pose>
    <truncated>0</truncated>
    <difficult>0</difficult>
    <bndbox>
      <xmin>375.45</xmin>
      <ymin>2.27</ymin>
      <xmax>556.36</xmax>
      <ymax>248.18</ymax>
    </bndbox>
  </object>
  <object>
    <name>shoe</name>
    <pose>Unspecified</pose>
    <truncated>0</truncated>
    <difficult>0</difficult>
    <bndbox>
      <xmin>383.64</xmin>
      <ymin>184.09</ymin>
      <xmax>550.00</xmax>
      <ymax>245.91</ymax>
    </bndbox>
  </object>
  <object>
    <name>bed</name>
    <pose>Unspecified</pose>
    <truncated>0</truncated>
    <difficult>0</difficult>
    <bndbox>
      <xmin>1.82</xmin>
      <ymin>0.91</ymin>
      <xmax>307.73</xmax>
      <ymax>210.45</ymax>
    </bndbox>
  </object>
</annotation>